npr/__init__.py
npr-2.3.0.dist-info/DESCRIPTION.rst
npr-2.3.0.dist-info/METADATA
npr-2.3.0.dist-info/RECORD
npr-2.3.0.dist-info/WHEEL
npr-2.3.0.dist-info/metadata.json
npr-2.3.0.dist-info/top_level.txt
