Metadata-Version: 2.0
Name: npr
Version: 2.3.0
Summary: NPR cloud framework
Home-page: http://github.com/perrydc/npr
Author: Demian Perry
Author-email: dperry@npr.org
License: MIT
Keywords: public,radio,stream,metadata,api,service,npr
Platform: UNKNOWN
Classifier: Development Status :: 5 - Production/Stable
Classifier: Intended Audience :: Developers
Classifier: License :: OSI Approved :: MIT License
Classifier: Programming Language :: Python :: 2
Classifier: Programming Language :: Python :: 2.7
Classifier: Programming Language :: Python :: 3
Classifier: Programming Language :: Python :: 3.3
Classifier: Programming Language :: Python :: 3.4
Classifier: Programming Language :: Python :: 3.5
Classifier: Programming Language :: Python :: 3.6
Classifier: Topic :: Internet :: WWW/HTTP
Requires-Dist: algoliasearch
Requires-Dist: future
Requires-Dist: requests
Requires-Dist: requests[security]; python_version < "2.9"
